datasette_jq/__init__.py
datasette_jq-0.2.1.dist-info/LICENSE
datasette_jq-0.2.1.dist-info/METADATA
datasette_jq-0.2.1.dist-info/WHEEL
datasette_jq-0.2.1.dist-info/entry_points.txt
datasette_jq-0.2.1.dist-info/top_level.txt
datasette_jq-0.2.1.dist-info/RECORD
