Metadata-Version: 2.1
Name: datasette-jq
Version: 0.2.1
Summary: Datasette plugin that adds custom SQL functions for executing jq expressions against JSON values
Home-page: https://github.com/simonw/datasette-jq
Author: Simon Willison
License: Apache License, Version 2.0
Platform: UNKNOWN
Requires-Dist: datasette
Requires-Dist: pyjq
Requires-Dist: six
Provides-Extra: test
Requires-Dist: pytest ; extra == 'test'
